gandai/__init__.py
gandai/analytics.py
gandai/constants.py
gandai/db.py
gandai/google.py
gandai/gpt.py
gandai/grata.py
gandai/helpers.py
gandai/main.py
gandai/models.py
gandai/query.py
gandai/reporting.py
gandai/secrets.py
gandai/tasks.py
gandai/visualize.py
gandai/__pycache__/__init__.cpython-311.pyc
gandai/__pycache__/adapters.cpython-311.pyc
gandai/__pycache__/analytics.cpython-311.pyc
gandai/__pycache__/auth.cpython-311.pyc
gandai/__pycache__/constants.cpython-311.pyc
gandai/__pycache__/datastore.cpython-311.pyc
gandai/__pycache__/db.cpython-311.pyc
gandai/__pycache__/google.cpython-311.pyc
gandai/__pycache__/gpt.cpython-311.pyc
gandai/__pycache__/grata.cpython-311.pyc
gandai/__pycache__/helpers.cpython-311.pyc
gandai/__pycache__/main.cpython-311.pyc
gandai/__pycache__/models.cpython-311.pyc
gandai/__pycache__/query.cpython-311.pyc
gandai/__pycache__/reporting.cpython-311.pyc
gandai/__pycache__/secrets.cpython-311.pyc
gandai/__pycache__/services.cpython-311.pyc
gandai/__pycache__/sources.cpython-311.pyc
gandai/__pycache__/tasks.cpython-311.pyc
gandai/__pycache__/visualizations.cpython-311.pyc
gandai/__pycache__/visualize.cpython-311.pyc
gandai/migrations/__init__.py
gandai/migrations/db_create.py
gandai/migrations/db_seed.py
gandai/migrations/dealcloud.py
gandai/migrations/__pycache__/__init__.cpython-311.pyc
gandai/migrations/__pycache__/dealcloud.cpython-311.pyc
gandai/migrations/sql/2305023-alter.sql
gandai/migrations/sql/230818-alter.sql
gandai/migrations/sql/240523-alter.sql
gandai/migrations/sql/schema.sql
gandai-1.7.83.dist-info/METADATA
gandai-1.7.83.dist-info/WHEEL
gandai-1.7.83.dist-info/top_level.txt
gandai-1.7.83.dist-info/RECORD
