Metadata-Version: 2.1
Name: gandai
Version: 1.7.83
Summary: TargetSelect
Author: Parker Holcomb
Author-email: Parker Holcomb <parker.holcomb@gmail.com>
Requires-Python: >=3.7
